spall/__init__.py
spall/_subprocess.py
spall/_version.py
spall/exceptions.py
spall/py.typed
spall-0.6.1.dist-info/LICENSE
spall-0.6.1.dist-info/METADATA
spall-0.6.1.dist-info/WHEEL
spall-0.6.1.dist-info/RECORD
