Metadata-Version: 2.1
Name: spall
Version: 0.6.1
Summary: Object-oriented commandline
Home-page: https://pypi.org/project/spall/
License: MIT
Keywords: commandline,oop,popen,run,subprocess
Author: jshwi
Author-email: stephen@jshwisolutions.com
Maintainer: jshwi
Maintainer-email: stephen@jshwisolutions.com
Requires-Python: >=3.8,<4.0
Classifier: License :: OSI Approved :: MIT License
Classifier: Programming Language :: Python :: 3
Classifier: Programming Language :: Python :: 3.8
Classifier: Programming Language :: Python :: 3.9
Classifier: Programming Language :: Python :: 3.10
Classifier: Programming Language :: Python :: 3.11
Project-URL: Documentation, https://spall.readthedocs.io/en/latest
Project-URL: Repository, https://github.com/jshwi/spall
